HardLinks/__init__.py
HardLinks/hard_links.py
HardLinks-0.0.1.dist-info/LICENSE
HardLinks-0.0.1.dist-info/METADATA
HardLinks-0.0.1.dist-info/WHEEL
HardLinks-0.0.1.dist-info/entry_points.txt
HardLinks-0.0.1.dist-info/top_level.txt
HardLinks-0.0.1.dist-info/RECORD
