Metadata-Version: 2.1
Name: HardLinks
Version: 0.0.1
Summary: Make hard links for specific file types for programs that don't search subdirectories.
Home-page: https://gitlab.com/coreman14/hardlinks
Author: Coreman14
Author-email: 
License: Apache License 2.0
Platform: UNKNOWN
Classifier: Programming Language :: Python :: 3
Classifier: Programming Language :: Python :: 3 :: Only
Classifier: Programming Language :: Python :: 3.5
Classifier: Programming Language :: Python :: 3.6
Classifier: Programming Language :: Python :: 3.7
Classifier: Programming Language :: Python :: 3.8
Classifier: Programming Language :: Python :: 3.9
Classifier: Programming Language :: Python :: 3.10
Classifier: Operating System :: OS Independent
Requires-Python: >=3.5
License-File: LICENSE
Requires-Dist: colorama (==0.4.4)
Requires-Dist: pywin32 (==302)
